simple_schedule/__init__.py
simple_schedule/__utils.py
simple_schedule/http_protocol_handler.py
simple_schedule/http_request_handler.py
simple_schedule/http_server.py
simple_schedule/logger.py
simple_schedule/work_node.py
simple_schedule/sense/__init__.py
simple_schedule/sense/echo.py
simple_schedule/sense/http_erro.py
simple_schedule-0.0.1.dist-info/LICENSE
simple_schedule-0.0.1.dist-info/METADATA
simple_schedule-0.0.1.dist-info/WHEEL
simple_schedule-0.0.1.dist-info/top_level.txt
simple_schedule-0.0.1.dist-info/RECORD
