Metadata-Version: 2.1
Name: simple-schedule
Version: 0.0.1
Summary: This is a simple python schedule.
Home-page: UNKNOWN
Author: tank
Author-email: cuidt@outlook.com
License: UNKNOWN
Platform: UNKNOWN
Classifier: Programming Language :: Python :: 3.7
Classifier: Programming Language :: Python :: 3.8
Classifier: Programming Language :: Python :: 3.9
Classifier: License :: OSI Approved :: MIT License
Classifier: Operating System :: OS Independent
Requires-Python: >=3.7
License-File: LICENSE
